<?xml version="1.0" encoding="UTF-8"?>
<timecycle_modifier_data version="1.000000">
  <modifier name="ll_timecycle" numMods="19" userFlags="0">
    <light_artificial_int_down_col_r>1.000 1.000</light_artificial_int_down_col_r>
    <light_artificial_int_down_col_g>0.816 1.000</light_artificial_int_down_col_g>
    <light_artificial_int_down_col_b>0.471 1.000</light_artificial_int_down_col_b>
    <light_artificial_int_down_intensity>0.600 0.000</light_artificial_int_down_intensity>
    <light_artificial_int_up_col_r>0.839 1.000</light_artificial_int_up_col_r>
    <light_artificial_int_up_col_g>0.859 1.000</light_artificial_int_up_col_g>
    <light_artificial_int_up_col_b>0.875 1.000</light_artificial_int_up_col_b>
    <light_artificial_int_up_intensity>0.100 0.000</light_artificial_int_up_intensity>
    <light_direction_override>0.000 0.000</light_direction_override>
    <postfx_bright_pass_thresh_width>0.500 0.000</postfx_bright_pass_thresh_width>
    <postfx_bright_pass_thresh>0.500 0.000</postfx_bright_pass_thresh>
    <postfx_intensity_bloom>0.500 0.000</postfx_intensity_bloom>
    <fog_start>70.000 70.000</fog_start>
    <far_clip>0.000 900.000</far_clip>
    <natural_ambient_multiplier>0.000 0.000</natural_ambient_multiplier>
    <artificial_int_ambient_multiplier>0.478 0.000</artificial_int_ambient_multiplier>
  </modifier>
    <modifier name="ll_timecycle2" numMods="19" userFlags="0">
    <light_artificial_int_down_col_r>1.000 1.000</light_artificial_int_down_col_r>
    <light_artificial_int_down_col_g>0.816 1.000</light_artificial_int_down_col_g>
    <light_artificial_int_down_col_b>0.471 1.000</light_artificial_int_down_col_b>
    <light_artificial_int_down_intensity>0.600 0.000</light_artificial_int_down_intensity>
    <light_artificial_int_up_col_r>0.839 1.000</light_artificial_int_up_col_r>
    <light_artificial_int_up_col_g>0.859 1.000</light_artificial_int_up_col_g>
    <light_artificial_int_up_col_b>0.875 1.000</light_artificial_int_up_col_b>
    <light_artificial_int_up_intensity>0.100 0.000</light_artificial_int_up_intensity>
    <light_direction_override>0.000 0.000</light_direction_override>
    <postfx_bright_pass_thresh_width>0.500 0.000</postfx_bright_pass_thresh_width>
    <postfx_bright_pass_thresh>0.500 0.000</postfx_bright_pass_thresh>
    <postfx_intensity_bloom>0.500 0.000</postfx_intensity_bloom>
    <fog_start>70.000 70.000</fog_start>
    <far_clip>0.000 200.000</far_clip>
    <natural_ambient_multiplier>0.000 0.000</natural_ambient_multiplier>
    <artificial_int_ambient_multiplier>0.478 0.000</artificial_int_ambient_multiplier>
  </modifier>
</timecycle_modifier_data>